setup.py
edgemanage/__init__.py
edgemanage/const.py
edgemanage/decisionmaker.py
edgemanage/edge_conf
edgemanage/edge_manage
edgemanage/edge_query
edgemanage/edgelist.py
edgemanage/edgemanage.py
edgemanage/edgestate.py
edgemanage/edgetest.py
edgemanage/statefile.py
edgemanage/util.py
edgemanage.egg-info/PKG-INFO
edgemanage.egg-info/SOURCES.txt
edgemanage.egg-info/dependency_links.txt
edgemanage.egg-info/not-zip-safe
edgemanage.egg-info/requires.txt
edgemanage.egg-info/top_level.txt
edgemanage/templates/zonetemplate.j2