Metadata-Version: 1.1
Name: edgemanage
Version: 2.0.7
Summary: HTTP availability management tool
Home-page: http://github.com/equalitie/edgemanage
Author: Hugh Nowlan
Author-email: nosmo@nosmo.me
License: Hacktivismo Enhanced-Source Software License Agreement
Keywords: edgemanage deflect DNS
Platform: UNKNOWN
Classifier: Development Status :: 5 - Production/Stable
Classifier: Intended Audience :: Developers
Classifier: Intended Audience :: System Administrators
Classifier: Topic :: Internet :: Name Service (DNS)
Classifier: Topic :: Utilities
